rerun_loader_urdf/__init__.py
rerun_loader_urdf/_ros_utils.py
rerun_loader_urdf-0.1.1.dist-info/METADATA
rerun_loader_urdf-0.1.1.dist-info/WHEEL
rerun_loader_urdf-0.1.1.dist-info/entry_points.txt
rerun_loader_urdf-0.1.1.dist-info/licenses/LICENSE
rerun_loader_urdf-0.1.1.dist-info/RECORD
