Metadata-Version: 2.4
Name: rerun-loader-urdf
Version: 0.1.1
Summary: An example data-loader plugin that lets you view URDF files in Rerun
License-File: LICENSE
Requires-Python: >=3.11
Requires-Dist: lxml>=5.3.1
Requires-Dist: numpy>=1.23
Requires-Dist: pillow>=11.1.0
Requires-Dist: pycollada>=0.9
Requires-Dist: pyyaml>=6.0.2
Requires-Dist: rerun-sdk>=0.22.0
Requires-Dist: scipy>=1.15.2
Requires-Dist: trimesh>=4.6.2
Requires-Dist: urdfdom-py
Requires-Dist: xacro>=1.13.3
